ovos_adapt/__init__.py
ovos_adapt/context.py
ovos_adapt/engine.py
ovos_adapt/entity_tagger.py
ovos_adapt/expander.py
ovos_adapt/intent.py
ovos_adapt/opm.py
ovos_adapt/parser.py
ovos_adapt/version.py
ovos_adapt/tools/__init__.py
ovos_adapt/tools/debug/__init__.py
ovos_adapt/tools/text/__init__.py
ovos_adapt/tools/text/tokenizer.py
ovos_adapt/tools/text/trie.py
ovos_adapt_parser-1.0.8.dist-info/LICENSE.md
ovos_adapt_parser-1.0.8.dist-info/METADATA
ovos_adapt_parser-1.0.8.dist-info/WHEEL
ovos_adapt_parser-1.0.8.dist-info/entry_points.txt
ovos_adapt_parser-1.0.8.dist-info/top_level.txt
ovos_adapt_parser-1.0.8.dist-info/RECORD
