Metadata-Version: 2.1
Name: ovos-adapt-parser
Version: 1.0.8
Summary: A text-to-intent parsing framework.
Home-page: https://github.com/OpenVoiceOS/ovos-adapt-pipeline-plugin
Author: Sean Fitzgerald
License: Apache License 2.0
Keywords: natural language processing
Classifier: Development Status :: 5 - Production/Stable
Classifier: Intended Audience :: Developers
Classifier: Topic :: Text Processing :: Linguistic
Classifier: License :: OSI Approved :: Apache Software License
Classifier: Programming Language :: Python :: 2.7
Classifier: Programming Language :: Python :: 3.5
Classifier: Programming Language :: Python :: 3.6
Classifier: Programming Language :: Python :: 3.7
Classifier: Programming Language :: Python :: 3.8
Classifier: Programming Language :: Python :: 3.9
License-File: LICENSE.md
Requires-Dist: six>=1.10.0
Requires-Dist: ovos-plugin-manager<2.0.0,>=0.5.0
Requires-Dist: ovos-workshop<8.0.0,>=0.1.7
Requires-Dist: ovos-utils<1.0.0,>=0.3.4
Requires-Dist: langcodes
